CD_to_Spotify_and_EBay/CD_to_Spotify_and_EBay.py
CD_to_Spotify_and_EBay/__init__.py
CD_to_Spotify_and_EBay-1.1.1.dist-info/METADATA
CD_to_Spotify_and_EBay-1.1.1.dist-info/WHEEL
CD_to_Spotify_and_EBay-1.1.1.dist-info/top_level.txt
CD_to_Spotify_and_EBay-1.1.1.dist-info/RECORD
