Metadata-Version: 2.1
Name: CD-to-Spotify-and-EBay
Version: 1.1.1
Summary: Transfer the songs from your old CDs to a Spotify Playlist and list the CDs on eBay
Home-page: UNKNOWN
Author: Alexander Halpern
Author-email: <halperna22@gmail.com>
License: UNKNOWN
Keywords: python,spotify,ebay
Platform: UNKNOWN
Classifier: Development Status :: 3 - Alpha
Classifier: Intended Audience :: End Users/Desktop
Classifier: Programming Language :: Python :: 3
Classifier: Operating System :: Unix
Classifier: Operating System :: MacOS :: MacOS X
Classifier: Operating System :: Microsoft :: Windows
Requires-Dist: spotipy
Requires-Dist: PyYAML
Requires-Dist: ebaysdk
Requires-Dist: pyserial
